{
    "time": {
        "cpu_time_user": "00:00:06.719",
        "cpu_time_system": "00:00:00.120",
        "runtime": "00:00:08.260",
        "cpu_time_iowait": "00:00:00.000"
    },
    "peak_resources": {
        "cpu_percent": 108.7,
        "memory_rss": "192MiB",
        "memory_vms": "333MiB",
        "threads": 2
    },
    "avg_resources": {
        "cpu_percent": 80.7144578313253,
        "memory_rss": "177MiB",
        "memory_vms": "315MiB",
        "threads": 1.9518072289156627
    }
}